erutils/__init__.py
erutils/__main__.py
erutils/config.py
erutils/flax_utils.py
erutils/lightning.py
erutils/loggers.py
erutils/nn.py
erutils/utils.py
erutils-1.4.0.dist-info/METADATA
erutils-1.4.0.dist-info/WHEEL
erutils-1.4.0.dist-info/top_level.txt
erutils-1.4.0.dist-info/RECORD
