Metadata-Version: 2.1
Name: erutils
Version: 1.4.0
Summary: UNKNOWN
Home-page: https://github.com/erfanzar/
Author: Erfan Zare Chavoshi
Author-email: erfanzare82@yahoo.com
License: Apache License 2.0
Platform: UNKNOWN
Classifier: Programming Language :: Python :: 3
Classifier: License :: OSI Approved :: MIT License
Classifier: Operating System :: OS Independent
Classifier: Programming Language :: Python :: 3
Classifier: Programming Language :: Python :: 3.6
Classifier: Programming Language :: Python :: 3.7
Classifier: Programming Language :: Python :: 3.8
Classifier: Programming Language :: Python :: 3.9
Classifier: Programming Language :: Python :: 3.10
Requires-Python: >=3.6, <3.11
Requires-Dist: PyYAML
Requires-Dist: json5
Requires-Dist: matplotlib
Requires-Dist: nltk
Requires-Dist: numba
Requires-Dist: numpy
Requires-Dist: onnxruntime
Requires-Dist: pandas
Requires-Dist: thop
Requires-Dist: torchaudio (>=0.9.0)
Requires-Dist: torchtext
Requires-Dist: torchvision (>=1.13.0)
